{"AF":"阿富汗","AX":"ÅLAND ISLANDS","AL":"ALBANIA","DZ":"阿尔及利亚","AS":"AMERICAN SAMOA","AD":"安道尔","AO":"安哥拉","AI":"安圭拉岛","AQ":"ANTARCTICA","AG":"安提瓜和巴布达","AR":"阿根廷","AM":"ARMENIA","AW":"ARUBA","AU":"澳大利亚","AT":"奥地利","AZ":"阿塞拜疆","BS":"BAHAMAS","BH":"巴林","BD":"孟加拉国","BB":"BARBADOS","BY":"白俄罗斯","BE":"比利时","BZ":"BELIZE","BJ":"BENIN","BM":"BERMUDA","BT":"BHUTAN","BO":"BOLIVIA, PLURINATIONAL STATE OF","BQ":"BONAIRE, SINT EUSTATIUS AND SABA","BA":"波黑","BW":"博茨瓦纳","BV":"BOUVET ISLAND","BR":"BRAZIL","IO":"BRITISH INDIAN OCEAN TERRITORY","BN":"BRUNEI DARUSSALAM","BG":"保加利亚","BF":"BURKINA FASO","BI":"BURUNDI","KH":"柬埔寨","CM":"喀麦隆","CA":"加拿大","CV":"CAPE VERDE","KY":"CAYMAN ISLANDS","CF":"中非共和国","TD":"CHAD","CL":"智利","CN":"中国","CX":"CHRISTMAS ISLAND","CC":"COCOS (KEELING) ISLANDS","CO":"哥伦比亚","KM":"COMOROS","CG":"CONGO","CD":"CONGO, THE DEMOCRATIC REPUBLIC OF THE","CK":"COOK ISLANDS","CR":"COSTA RICA","CI":"科特迪瓦","HR":"克罗地亚","CU":"CUBA","CW":"CURAÇAO","CY":"塞浦路斯","CZ":"捷克","DK":"丹麦","DJ":"DJIBOUTI","DM":"DOMINICA","DO":"DOMINICAN REPUBLIC","EC":"ECUADOR","EG":"埃及","SV":"EL SALVADOR","GQ":"EQUATORIAL GUINEA","ER":"ERITREA","EE":"ESTONIA","ET":"ETHIOPIA","FK":"FALKLAND ISLANDS (MALVINAS)","FO":"FAROE ISLANDS","FJ":"FIJI","FI":"芬兰","FR":"法国","GF":"FRENCH GUIANA","PF":"FRENCH POLYNESIA","TF":"FRENCH SOUTHERN TERRITORIES","GA":"GABON","GM":"GAMBIA","GE":"GEORGIA","DE":"德国","GH":"GHANA","GI":"GIBRALTAR","GR":"希腊","GL":"GREENLAND","GD":"GRENADA","GP":"GUADELOUPE","GU":"GUAM","GT":"GUATEMALA","GG":"GUERNSEY","GN":"GUINEA","GW":"GUINEA-BISSAU","GY":"GUYANA","HT":"HAITI","HM":"HEARD ISLAND AND MCDONALD ISLANDS","VA":"HOLY SEE (VATICAN CITY STATE)","HN":"HONDURAS","HK":"HONG KONG","HU":"匈牙利","IS":"ICELAND","IN":"印度","ID":"印度尼西亚","IR":"伊朗","IQ":"伊拉克","IE":"爱尔兰","IM":"ISLE OF MAN","IL":"以色列","IT":"意大利","JM":"JAMAICA","JP":"日本","JE":"JERSEY","JO":"JORDAN","KZ":"KAZAKHSTAN","KE":"KENYA","KI":"KIRIBATI","KP":"朝鲜","KR":"韩国","KW":"科威特","KG":"吉尔吉斯斯坦","LA":"LAO PEOPLE'S DEMOCRATIC REPUBLIC","LV":"LATVIA","LB":"黎巴嫩","LS":"LESOTHO","LR":"LIBERIA","LY":"LIBYA","LI":"LIECHTENSTEIN","LT":"LITHUANIA","LU":"LUXEMBOURG","MO":"MACAO","MK":"MACEDONIA, THE FORMER YUGOSLAV REPUBLIC OF","MG":"MADAGASCAR","MW":"MALAWI","MY":"马来西亚","MV":"MALDIVES","ML":"MALI","MT":"MALTA","MH":"MARSHALL ISLANDS","MQ":"MARTINIQUE","MR":"MAURITANIA","MU":"MAURITIUS","YT":"MAYOTTE","MX":"墨西哥","FM":"MICRONESIA, FEDERATED STATES OF","MD":"MOLDOVA, REPUBLIC OF","MC":"MONACO","MN":"MONGOLIA","ME":"MONTENEGRO","MS":"MONTSERRAT","MA":"MOROCCO","MZ":"MOZAMBIQUE","MM":"MYANMAR","NA":"NAMIBIA","NR":"NAURU","NP":"尼泊尔","NL":"荷兰","NC":"NEW CALEDONIA","NZ":"新西兰","NI":"NICARAGUA","NE":"NIGER","NG":"尼日利亚","NU":"NIUE","NF":"NORFOLK ISLAND","MP":"NORTHERN MARIANA ISLANDS","NO":"挪威","OM":"阿曼","PK":"巴基斯坦","PW":"PALAU","PS":"PALESTINIAN TERRITORY, OCCUPIED","PA":"PANAMA","PG":"PAPUA NEW GUINEA","PY":"PARAGUAY","PE":"PERU","PH":"菲律宾","PN":"PITCAIRN","PL":"波兰","PT":"葡萄牙","PR":"PUERTO RICO","QA":"卡塔尔","RE":"RÉUNION","RO":"ROMANIA","RU":"俄罗斯","RW":"RWANDA","BL":"SAINT BARTHÉLEMY","SH":"SAINT HELENA, ASCENSION AND TRISTAN DA CUNHA","KN":"SAINT KITTS AND NEVIS","LC":"SAINT LUCIA","MF":"SAINT MARTIN (FRENCH PART)","PM":"SAINT PIERRE AND MIQUELON","VC":"SAINT VINCENT AND THE GRENADINES","WS":"SAMOA","SM":"SAN MARINO","ST":"SAO TOME AND PRINCIPE","SA":"沙特阿拉伯","SN":"SENEGAL","RS":"塞尔维亚","SC":"SEYCHELLES","SL":"SIERRA LEONE","SG":"新加坡","SX":"SINT MAARTEN (DUTCH PART)","SK":"斯洛伐克","SI":"SLOVENIA","SB":"SOLOMON ISLANDS","SO":"SOMALIA","ZA":"SOUTH AFRICA","GS":"SOUTH GEORGIA AND THE SOUTH SANDWICH ISLANDS","SS":"SOUTH SUDAN","ES":"西班牙","LK":"斯里兰卡","SD":"SUDAN","SR":"SURINAME","SJ":"SVALBARD AND JAN MAYEN","SZ":"SWAZILAND","SE":"瑞典","CH":"瑞士","SY":"SYRIAN ARAB REPUBLIC","TW":"中国台湾","TJ":"TAJIKISTAN","TZ":"TANZANIA, UNITED REPUBLIC OF","TH":"泰国","TL":"TIMOR-LESTE","TG":"TOGO","TK":"TOKELAU","TO":"TONGA","TT":"TRINIDAD AND TOBAGO","TN":"TUNISIA","TR":"土耳其","TM":"TURKMENISTAN","TC":"TURKS AND CAICOS ISLANDS","TV":"TUVALU","UG":"乌干达","UA":"乌克兰","AE":"阿联酋","GB":"UNITED KINGDOM","US":"美国","UM":"UNITED STATES MINOR OUTLYING ISLANDS","UY":"URUGUAY","UZ":"UZBEKISTAN","VU":"VANUATU","VE":"VENEZUELA, BOLIVARIAN REPUBLIC OF","VN":"VIET NAM","VG":"VIRGIN ISLANDS, BRITISH","VI":"VIRGIN ISLANDS, U.S.","WF":"WALLIS AND FUTUNA","EH":"WESTERN SAHARA","YE":"YEMEN","ZM":"ZAMBIA","ZW":"ZIMBABWE"}